sigma/backends/azure/__init__.py
sigma/backends/azure/azure.py
sigma/pipelines/azure/__init__.py
sigma/pipelines/azure/azure.py
pysigma_backend_azure-0.1.3.dist-info/LICENSE
pysigma_backend_azure-0.1.3.dist-info/METADATA
pysigma_backend_azure-0.1.3.dist-info/WHEEL
pysigma_backend_azure-0.1.3.dist-info/RECORD
